<?xml version="1.0" encoding="UTF-8"?>
<beans xmlns="http://www.springframework.org/schema/beans"
       xmlns:xsi="http://www.w3.org/2001/XMLSchema-instance"
       xmlns:context="http://www.springframework.org/schema/context"
       xmlns:mvc="http://www.springframework.org/schema/mvc" xmlns:jpa="http://www.springframework.org/schema/data/jpa"
       xmlns:tx="http://www.springframework.org/schema/tx"
       xsi:schemaLocation="http://www.springframework.org/schema/beans http://www.springframework.org/schema/beans/spring-beans.xsd http://www.springframework.org/schema/context http://www.springframework.org/schema/context/spring-context.xsd http://www.springframework.org/schema/mvc http://www.springframework.org/schema/mvc/spring-mvc.xsd http://www.springframework.org/schema/data/jpa http://www.springframework.org/schema/data/jpa/spring-jpa.xsd http://www.springframework.org/schema/tx http://www.springframework.org/schema/tx/spring-tx.xsd">

    <context:component-scan base-package="com.loan.uts.controller"/>

    <context:component-scan base-package="com.loan.uts.service"/>
    <context:property-placeholder location="email.properties"/>

    <mvc:default-servlet-handler/>


    <mvc:annotation-driven/>

    <bean id="jspViewResolver" class="org.springframework.web.servlet.view.InternalResourceViewResolver">
        <property name="viewClass" value="org.springframework.web.servlet.view.JstlView"/>
        <property name="prefix" value="/WEB-INF/view/"/>
        <property name="suffix" value=".jsp"/>
    </bean>

    <jpa:repositories base-package="com.loan.uts.repository"/>

    <!-- 链接到persistence.xml -->
    <bean id="entityManagerFactory" class="org.springframework.orm.jpa.LocalEntityManagerFactoryBean">
        <property name="persistenceUnitName" value="defaultPersistenceUnit"/>
    </bean>



    <!-- 事务管理 -->
    <bean id="transactionManager" class="org.springframework.orm.jpa.JpaTransactionManager">
        <property name="entityManagerFactory" ref="entityManagerFactory"/>
    </bean>

    <bean id="javaMailSender" class="org.springframework.mail.javamail.JavaMailSenderImpl">
        <property name="host" value="${email.host}"/>
        <property name="username" value="${email.username}"/>
        <property name="password" value="${email.password}"/>
        <property name="port" value="${email.smtp.port}"/>
        <property name="javaMailProperties">
            <props>
                <prop key="mail.smtp.auth">true</prop>
                <prop key="mail.smtp.timeout">25000</prop>
                <prop key="mail.smtp.starttls.enable">true</prop>
                <prop key="mail.smtp.EnableSSL.enable">true</prop>
                <prop key="mail.smtp.socketFactory.class">javax.net.ssl.SSLSocketFactory</prop>
                <prop key="mail.smtp.socketFactory.fallback">false</prop>
                <prop key="mail.smtp.socketFactory.port">465</prop>
            </props>
        </property>
    </bean>


    <!--配置线程池-->
    <bean id="taskExecutor" class="org.springframework.scheduling.concurrent.ThreadPoolTaskExecutor">
        <!-- 核心线程数 -->
        <property name="corePoolSize" value="10" />
        <!-- 最大线程数 -->
        <property name="maxPoolSize" value="100" />
        <!-- 最大队列数 -->
        <property name="queueCapacity" value="500" />
        <!-- 线程池维护线程所允许的空闲时间 -->
        <property name="keepAliveSeconds" value="60" />
    </bean>

    <!-- 开启事务管理注解 -->
    <tx:annotation-driven transaction-manager="transactionManager"/>
</beans>